{
  "resourceType" : "CodeSystem",
  "id" : "beec6aef-ec7d-4296-94c7-f9b6d2fc3301-30",
  "url" : "http://hl7.org/fhir/comparison/CodeSystem/beec6aef-ec7d-4296-94c7-f9b6d2fc3301-30",
  "name" : "IntersectionTDDUITaskOutputBilanAndTDDUITaskOutputBilan",
  "title" : "Intersection of TDDUI Task Output Bilan And TDDUI Task Output Bilan",
  "status" : "active",
  "date" : "2026-02-24T10:24:43+00:00",
  "jurisdiction" : [{
    "coding" : [{
      "system" : "urn:iso:std:iso:3166",
      "code" : "FR",
      "display" : "FRANCE"
    }]
  }],
  "concept" : [{
    "code" : "syntheseBilan",
    "display" : "Synthèse du bilan."
  }]
}