{
  "resourceType" : "CodeSystem",
  "id" : "d55a3a53-c2d6-4471-a929-f22a6a751a92-20",
  "url" : "http://hl7.org/fhir/comparison/CodeSystem/d55a3a53-c2d6-4471-a929-f22a6a751a92-20",
  "name" : "UnionTDDUITaskInputMoyenRessourceAndTDDUITaskInputMoyenRessource",
  "title" : "Union of TDDUI Task Input Moyen Ressource And TDDUI Task Input Moyen Ressource",
  "status" : "active",
  "date" : "2026-02-10T10:29:04+00:00",
  "jurisdiction" : [{
    "coding" : [{
      "system" : "urn:iso:std:iso:3166",
      "code" : "FR",
      "display" : "FRANCE"
    }]
  }],
  "concept" : [{
    "code" : "titre",
    "display" : "Titre du moyen ou de la ressource à utiliser."
  },
  {
    "code" : "evaluation",
    "display" : "Evaluation du moyen ou de la ressource."
  },
  {
    "code" : "pieceJointe",
    "display" : "Pièce jointe du moyen/ressource."
  }]
}