<?xml version="1.0" encoding="UTF-8"?>

<CarePlan xmlns="http://hl7.org/fhir">
  <id value="tddui-careplan-projet-personnalise-pa-example"/>
  <meta>
    <profile value="https://interop.esante.gouv.fr/ig/fhir/tddui/StructureDefinition/tddui-careplan-projet-personnalise"/>
  </meta>
  <text>
    <status value="generated"/><div xmlns="http://www.w3.org/1999/xhtml"><p class="res-header-id"><b>Narratif généré : PlanDeSoins tddui-careplan-projet-personnalise-pa-example</b></p><a name="tddui-careplan-projet-personnalise-pa-example"> </a><a name="hctddui-careplan-projet-personnalise-pa-example"> </a><div style="display: inline-block; background-color: #d9e0e7; padding: 6px; margin: 4px; border: 1px solid #8da1b4; border-radius: 5px; line-height: 60%"><p style="margin-bottom: 0px"/><p style="margin-bottom: 0px">Profil: <a href="StructureDefinition-tddui-careplan-projet-personnalise.html">TDDUI CarePlan Projet Personalise</a></p></div><p><b>identifier</b>: <code>https://identifiant-medicosocial-projetpersonnalise.esante.gouv.fr</code>/3480787529/123456789-PPER-1234</p><p><b>status</b>: Active</p><p><b>intent</b>: Plan</p><p><b>title</b>: Projet personnalisé de Mme Jeanne L.</p><p><b>subject</b>: <a href="Patient-tddui-patient-pa-example-pp.html">Jeanne L. (official) Female, Date de Naissance inconnue ( Patient internal identifier: 3480787529/123456789)</a></p><p><b>supportingInfo</b>: <a href="Consent-tddui-consent-accord-example.html">Consentement structure</a></p></div>
  </text>
  <identifier>
    <system value="https://identifiant-medicosocial-projetpersonnalise.esante.gouv.fr"/>
    <value value="3480787529/123456789-PPER-1234"/>
  </identifier>
  <status value="active"/>
  <intent value="plan"/>
  <title value="Projet personnalisé de Mme Jeanne L."/>
  <subject>
    <reference value="Patient/tddui-patient-pa-example-pp"/>
  </subject>
  <supportingInfo>
    <reference value="Consent/tddui-consent-accord-example"/>
    <display value="Consentement structure"/>
  </supportingInfo>
</CarePlan>