{
  "resourceType" : "ValueSet",
  "id" : "44040f11-0401-48f1-85b4-5d358a57d562-60",
  "url" : "http://hl7.org/fhir/comparison/ValueSet/44040f11-0401-48f1-85b4-5d358a57d562-60",
  "name" : "IntersectionSpecialCourtesyAndSpecialCourtesy",
  "title" : "Intersection of Special courtesy And Special courtesy",
  "status" : "draft",
  "date" : "2025-11-03T10:50:34+00:00",
  "compose" : {
    "include" : [{
      "concept" : [{
        "code" : "EXT"
      },
      {
        "code" : "NRM"
      },
      {
        "code" : "PRF"
      },
      {
        "code" : "STF"
      },
      {
        "code" : "VIP"
      }]
    },
    {
      "concept" : [{
        "code" : "UNK"
      }]
    }]
  }
}